pydantic_pint/__init__.py
pydantic_pint/_version.py
pydantic_pint/quantity.py
pydantic_pint/registry.py
pydantic_pint/value.py
pydantic_pint-0.2.dist-info/licenses/LICENSE.md
pydantic_pint-0.2.dist-info/METADATA
pydantic_pint-0.2.dist-info/WHEEL
pydantic_pint-0.2.dist-info/top_level.txt
pydantic_pint-0.2.dist-info/RECORD
