Metadata-Version: 2.4
Name: pydantic-pint
Version: 0.2
Summary: Pydantic validation for Pint Quantities.
Author-email: Tyler Hughes <tylerxh111+git@proton.me>
License: MIT License
Project-URL: source, https://github.com/tylerh111/pydantic-pint
Project-URL: issues, https://github.com/tylerh111/pydantic-pint/issues
Project-URL: changes, https://github.com/tylerh111/pydantic-pint/blob/main/CHANGES.md
Project-URL: documentation, https://pydantic-pint.readthedocs.io
Keywords: pydantic-pint,pydantic,pint
Classifier: Development Status :: 1 - Planning
Classifier: Framework :: Pydantic
Classifier: Framework :: Pydantic :: 2
Classifier: Intended Audience :: Developers
Classifier: License :: OSI Approved :: MIT License
Classifier: Operating System :: OS Independent
Classifier: Programming Language :: Python
Classifier: Programming Language :: Python :: 3
Classifier: Programming Language :: Python :: 3.8
Classifier: Programming Language :: Python :: 3.9
Classifier: Programming Language :: Python :: 3.10
Classifier: Programming Language :: Python :: 3.11
Classifier: Programming Language :: Python :: 3.12
Classifier: Programming Language :: Python :: 3 :: Only
Classifier: Topic :: Scientific/Engineering
Classifier: Topic :: Software Development :: Libraries :: Python Modules
Classifier: Typing :: Typed
Requires-Python: >=3.8
License-File: LICENSE.md
Requires-Dist: pint>=0.20
Requires-Dist: pydantic>=2.0
Provides-Extra: build
Requires-Dist: build; extra == "build"
Requires-Dist: bumpver; extra == "build"
Requires-Dist: setuptools>=61; extra == "build"
Requires-Dist: setuptools-scm; extra == "build"
Requires-Dist: towncrier; extra == "build"
Requires-Dist: twine; extra == "build"
Provides-Extra: dev
Requires-Dist: nox; extra == "dev"
Requires-Dist: setuptools-scm; extra == "dev"
Requires-Dist: pydantic-pint[build,docs,lint,tests]; extra == "dev"
Provides-Extra: docs
Requires-Dist: mike; extra == "docs"
Requires-Dist: mkdocs; extra == "docs"
Requires-Dist: mkdocs-exclude; extra == "docs"
Requires-Dist: mkdocs-material; extra == "docs"
Requires-Dist: mkdocs-material-extensions; extra == "docs"
Requires-Dist: mkdocs-minify-plugin; extra == "docs"
Requires-Dist: mkdocs-redirects; extra == "docs"
Requires-Dist: mkdocstrings; extra == "docs"
Requires-Dist: mkdocstrings-python; extra == "docs"
Requires-Dist: pygments; extra == "docs"
Requires-Dist: pymdown-extensions; extra == "docs"
Provides-Extra: lint
Requires-Dist: ruff; extra == "lint"
Provides-Extra: tests
Requires-Dist: pytest; extra == "tests"
Requires-Dist: pytest-cov; extra == "tests"
Dynamic: license-file
